mdscribe/__init__.py
mdscribe/amber/__init__.py
mdscribe/helper/__init__.py
mdscribe/helper/cli.py
mdscribe/helper/conserved_water.py
mdscribe/helper/coord.py
mdscribe/helper/mol2file.py
mdscribe/helper/pdb-mcsym.py
mdscribe/helper/pdb-merge.py
mdscribe/helper/pdbfile.py
mdscribe/helper/svg.py
mdscribe/openmm/__init__.py
mdscribe/openmm/atm.py
mdscribe/openmm/config.py
mdscribe/openmm/hremd.py
mdscribe/openmm/omm.py
mdscribe/openmm/simulate.py
mdscribe/openmm/solvate.py
mdscribe/ternary/__init__.py
mdscribe/ternary/complex.py
mdscribe-0.7.4.dist-info/licenses/LICENSE
mdscribe-0.7.4.dist-info/METADATA
mdscribe-0.7.4.dist-info/WHEEL
mdscribe-0.7.4.dist-info/entry_points.txt
mdscribe-0.7.4.dist-info/top_level.txt
mdscribe-0.7.4.dist-info/RECORD
