Metadata-Version: 2.4
Name: mdscribe
Version: 0.7.4
Summary: A Toolset For Molecular Dynamics
Author-email: Sung-Hun Bae <sunghun.bae@gmail.com>
Maintainer-email: Sung-Hun Bae <sunghun.bae@gmail.com>
License-Expression: MIT
Project-URL: Homepage, https://github.com/sunghunbae/mdscribe
Project-URL: Repository, https://github.com/sunghunbae/mdscribe.git
Project-URL: Issues, https://github.com/sunghunbae/mdscribe/issues
Project-URL: Changelog, https://github.com/sunghunbae/mdscribe/blob/master/CHANGELOG.md
Project-URL: Documentation, https://sunghunbae.github.io/mdscribe/
Keywords: Molecular Dynamics,OpenMM,PROTAC,Ternary Complex Modeling
Classifier: Development Status :: 3 - Alpha
Classifier: Intended Audience :: Developers
Classifier: Programming Language :: Python :: 3
Classifier: Operating System :: OS Independent
Requires-Python: >=3.11
License-File: LICENSE
Requires-Dist: scipy
Requires-Dist: biopython
Requires-Dist: pypdb
Requires-Dist: numpy
Requires-Dist: rdkit>=2025.3.1
Requires-Dist: openmm
Requires-Dist: mkdocstrings-python
Requires-Dist: pytest
Dynamic: license-file
